mbforbes_python_utils/__init__.py
mbforbes_python_utils/mbforbes_python_utils.py
mbforbes_python_utils/py.typed
mbforbes_python_utils-0.5.0.dist-info/LICENSE.txt
mbforbes_python_utils-0.5.0.dist-info/METADATA
mbforbes_python_utils-0.5.0.dist-info/WHEEL
mbforbes_python_utils-0.5.0.dist-info/top_level.txt
mbforbes_python_utils-0.5.0.dist-info/RECORD
