Metadata-Version: 2.1
Name: mbforbes-python-utils
Version: 0.5.0
Summary: Some tiny python utils so I can be lazier.
Home-page: https://github.com/mbforbes/python-utils
Author: Maxwell Forbes
License: MIT
Requires-Python: >=3.9
License-File: LICENSE.txt
